mobio_restart_pod/__main__.py
mobio_restart_pod/config/check_kafka_group_liveness.py
mobio_restart_pod-0.2.1.dist-info/METADATA
mobio_restart_pod-0.2.1.dist-info/WHEEL
mobio_restart_pod-0.2.1.dist-info/top_level.txt
mobio_restart_pod-0.2.1.dist-info/RECORD
