Metadata-Version: 2.1
Name: mobio-restart-pod
Version: 0.2.1
Summary: Restart pod kubernetes with kafka python
Home-page: https://github.com/mobiovn
Author: Mobio
Author-email: contact@mobio-restart-pod.vn
License: MIT
Project-URL: Source, https://github.com/mobiovn
Platform: UNKNOWN
Classifier: Development Status :: 3 - Alpha
Classifier: Intended Audience :: Developers
Classifier: Topic :: Software Development :: Build Tools
Classifier: License :: OSI Approved :: MIT License
Classifier: Programming Language :: Python :: 3
Classifier: Programming Language :: Python :: 3.6
Classifier: Programming Language :: Python :: 3.7
Classifier: Programming Language :: Python :: 3.8
Classifier: Programming Language :: Python :: 3.9
Classifier: Programming Language :: Python :: 3 :: Only
Requires-Python: >=3
